asyncio_scheduler/__init__.py
asyncio_scheduler/py.typed
asyncio_scheduler/scheduler.py
asyncio_scheduler/thread.py
asyncio_scheduler-1.0.4.dist-info/METADATA
asyncio_scheduler-1.0.4.dist-info/WHEEL
asyncio_scheduler-1.0.4.dist-info/licenses/LICENSE
asyncio_scheduler-1.0.4.dist-info/RECORD
