Metadata-Version: 2.3
Name: asyncio_scheduler
Version: 1.0.4
Summary: Asyncio scheduler with tasks
Project-URL: Repository, https://github.com/rendaduiyan-python/async_scheduler.git
Project-URL: Bug Tracker, https://github.com/rendaduiyan-python/async_scheduler/issues
Project-URL: Changelog, https://github.com/rendaduiyan-python/async_scheduler/CHANGELOG.md
Author-email: rendaduiyan <duiyanrenda@gmail.com>
Maintainer-email: rendaduiyan <duiyanrenda@gmail.com>
License: MIT License
License-File: LICENSE
Keywords: async,event loop,multi-threads,scheduler,tasks
Classifier: Development Status :: 4 - Beta
Classifier: Programming Language :: Python
Requires-Python: >=3.8
Requires-Dist: pytest-asyncio>=0.23.8
Requires-Dist: pytest>=8.3.2
Requires-Dist: tornado>=6.4.1
